pyer/__init__.py
pyer/json.py
pyer/parallel_timeseries_dacc.py
pyer/es/__init__.py
pyer/es/change_mapping.py
pyer/es/com.py
pyer/es/get.py
pyer/es/queries.py
pyer/es/scrap.py
pyer/ftp/__init__.py
pyer/ftp/get.py
pyer/mong/__init__.py
pyer/mong/agg.py
pyer/mong/com.py
pyer/mong/queries.py
pyer/mong/util.py
pyer/spark/__init__.py
pyer/spark/rdd_wrapper.py
pyer/spark/to.py
pyer/spark/util.py
pyer/xls/__init__.py
pyer/xls/manip.py
pyer/xls/read.py
pyer/xls/write.py
pyer-0.0.3.dist-info/LICENSE
pyer-0.0.3.dist-info/METADATA
pyer-0.0.3.dist-info/WHEEL
pyer-0.0.3.dist-info/top_level.txt
pyer-0.0.3.dist-info/RECORD
