Metadata-Version: 2.1
Name: pyer
Version: 0.0.3
Summary: Data accessors.
Home-page: https://github.com/thorwhalen/newut/tree/master/pyer
Author: Thor Whalen
License: mit
Platform: any
License-File: LICENSE
